llmthinkbench/__init__.py
llmthinkbench/cli.py
llmthinkbench/models/__init__.py
llmthinkbench/models/model_handler.py
llmthinkbench/tasks/__init__.py
llmthinkbench/tasks/absolute_difference_task.py
llmthinkbench/tasks/base_task.py
llmthinkbench/tasks/comparison_task.py
llmthinkbench/tasks/division_task.py
llmthinkbench/tasks/even_count_task.py
llmthinkbench/tasks/find_maximum_task.py
llmthinkbench/tasks/find_minimum_task.py
llmthinkbench/tasks/mean_task.py
llmthinkbench/tasks/median_task.py
llmthinkbench/tasks/mode_task.py
llmthinkbench/tasks/multiplication_task.py
llmthinkbench/tasks/odd_count_task.py
llmthinkbench/tasks/sorting_task.py
llmthinkbench/tasks/subtraction_task.py
llmthinkbench/tasks/sum_task.py
llmthinkbench/utils/__init__.py
llmthinkbench/utils/absolute_difference_parsing.py
llmthinkbench/utils/comparison_parsing.py
llmthinkbench/utils/division_parsing.py
llmthinkbench/utils/even_count_parsing.py
llmthinkbench/utils/find_maximum_parsing.py
llmthinkbench/utils/find_minimum_parsing.py
llmthinkbench/utils/logging_utils.py
llmthinkbench/utils/mean_parsing.py
llmthinkbench/utils/median_parsing.py
llmthinkbench/utils/mode_parsing.py
llmthinkbench/utils/multiplication_parsing.py
llmthinkbench/utils/odd_count_parsing.py
llmthinkbench/utils/reporting.py
llmthinkbench/utils/sorting_parsing.py
llmthinkbench/utils/subtraction_parsing.py
llmthinkbench/utils/sum_parsing.py
llmthinkbench-0.1.6.dist-info/licenses/LICENSE
llmthinkbench-0.1.6.dist-info/METADATA
llmthinkbench-0.1.6.dist-info/WHEEL
llmthinkbench-0.1.6.dist-info/entry_points.txt
llmthinkbench-0.1.6.dist-info/top_level.txt
llmthinkbench-0.1.6.dist-info/RECORD
