Metadata-Version: 2.4
Name: llmthinkbench
Version: 0.1.6
Summary: A framework for evaluating overthinking and basic reasoning capabilities of Large Language Models
Home-page: https://github.com/ctrl-gaurav/LLMThinkBench
Author: Gaurav Srivastava
Author-email: gauravhhh30@gmail.com
Project-URL: Bug Tracker, https://github.com/ctrl-gaurav/LLMThinkBench/issues
Classifier: Programming Language :: Python :: 3
Classifier: Operating System :: OS Independent
Classifier: Development Status :: 3 - Alpha
Classifier: Intended Audience :: Science/Research
Classifier: Topic :: Scientific/Engineering :: Artificial Intelligence
Requires-Python: >=3.10
License-File: LICENSE
Requires-Dist: vllm>=0.2.0
Requires-Dist: transformers>=4.30.0
Requires-Dist: numpy>=1.20.0
Requires-Dist: tqdm>=4.64.0
Requires-Dist: tabulate>=0.9.0
Dynamic: author
Dynamic: author-email
Dynamic: classifier
Dynamic: description
Dynamic: description-content-type
Dynamic: home-page
Dynamic: license-file
Dynamic: project-url
Dynamic: requires-dist
Dynamic: requires-python
Dynamic: summary
